emerge/__init__.py
emerge/__version__.py
emerge/cli/__init__.py
emerge/compute/__init__.py
emerge/core/__init__.py
emerge/core/client.py
emerge/core/objects.py
emerge/data/__init__.py
emerge/file/__init__.py
emerge/fs/__init__.py
emerge/fs/filesystem.py
emerge/node/__init__.py
emerge/node/handlers.py
emerge/node/server.py
emerge/tests/__init__.py
emerge/tests/test_client.py
emerge/zmq/__init__.py
emerge/zmq/connection.py
emerge/zmq/message.py
emerge/zmq/publisher.py
emerge/zmq/settings.py
emerge/zmq/subscriber.py
emergefs-0.0.5.dist-info/LICENSE
emergefs-0.0.5.dist-info/METADATA
emergefs-0.0.5.dist-info/WHEEL
emergefs-0.0.5.dist-info/entry_points.txt
emergefs-0.0.5.dist-info/top_level.txt
emergefs-0.0.5.dist-info/RECORD
