Metadata-Version: 2.1
Name: emergefs
Version: 0.0.5
Summary: Emerge Computational Filesystem.
Home-page: https://github.com/radiantone/emerge
Author: Darren Govoni
Author-email: darren@elasticcode.ai
License: MIT License
Keywords: cli,tools,utility
Platform: UNKNOWN
Classifier: Development Status :: 2 - Pre-Alpha
Classifier: Intended Audience :: Developers
Classifier: Programming Language :: Python :: 3.10
Requires-Python: >=3.9
License-File: LICENSE
Requires-Dist: black
Requires-Dist: click
Requires-Dist: flake8
Requires-Dist: isort
Requires-Dist: pytest
Requires-Dist: zerorpc
